[
  {
    "problem_name": "Bernstein-Vazirani",
    "description": "Find a hidden bitstring s in a function f(x) = s * x (mod 2).",
    "completed_at": "2026-06-12T20:42:10.469062Z",
    "success_rate": 1.0,
    "quantum_query_complexity": "O(1)",
    "quantum_gate_complexity": "O(N)",
    "speedup_type": "Linear",
    "synthesis_code": "from qiskit import QuantumCircuit\nqc = QuantumCircuit(N + 1, N)\nqc.x(N)\nqc.h(range(N + 1))\nqc.compose(oracle, inplace=True)\nqc.h(range(N))\nqc.measure(range(N), range(N))\n",
    "analysis_text": "The quantum algorithm runs in 1 query, whereas classical deterministic search requires N queries. Thus, we achieve a linear speedup. The gate complexity is linear O(N) due to the single-qubit Hadamard gates applied before and after the oracle.",
    "base_function_code": "def g(x, N):\n    return 0\n",
    "oracle_generator_code": "def make_oracle(secret, N):\n    def f(x):\n        dot = 0\n        for i in range(N):\n            if (secret & (1 << i)) and (x & (1 << i)):\n                dot ^= 1\n        return dot\n    return f\n"
  },
  {
    "problem_name": "Bernstein-Vazirani",
    "description": "Find a hidden bitstring s in a function f(x) = s * x (mod 2).",
    "completed_at": "2026-06-12T20:26:57.940000Z",
    "success_rate": 1.0,
    "quantum_query_complexity": "O(1)",
    "quantum_gate_complexity": "O(N)",
    "speedup_type": "Linear",
    "synthesis_code": "from qiskit import QuantumCircuit\nqc = QuantumCircuit(N + 1, N)\nqc.x(N)\nqc.h(range(N + 1))\nqc.compose(oracle, inplace=True)\nqc.h(range(N))\nqc.measure(range(N), range(N))\n",
    "analysis_text": "The quantum algorithm runs in 1 query, whereas classical deterministic search requires N queries. Thus, we achieve a linear speedup. The gate complexity is linear O(N) due to the single-qubit Hadamard gates applied before and after the oracle.",
    "base_function_code": "def g(x, N):\n    return 0\n",
    "oracle_generator_code": "def make_oracle(secret, N):\n    def f(x):\n        dot = 0\n        for i in range(N):\n            if (secret & (1 << i)) and (x & (1 << i)):\n                dot ^= 1\n        return dot\n    return f\n"
  },
  {
    "problem_name": "Bernstein-Vazirani",
    "description": "Find a hidden bitstring s in a function f(x) = s * x (mod 2).",
    "completed_at": "2026-06-12T20:11:45.385780Z",
    "success_rate": 1.0,
    "quantum_query_complexity": "O(1)",
    "quantum_gate_complexity": "O(N)",
    "speedup_type": "Linear",
    "synthesis_code": "from qiskit import QuantumCircuit\nqc = QuantumCircuit(N + 1, N)\nqc.x(N)\nqc.h(range(N + 1))\nqc.compose(oracle, inplace=True)\nqc.h(range(N))\nqc.measure(range(N), range(N))\n",
    "analysis_text": "The quantum algorithm runs in 1 query, whereas classical deterministic search requires N queries. Thus, we achieve a linear speedup. The gate complexity is linear O(N) due to the single-qubit Hadamard gates applied before and after the oracle.",
    "base_function_code": "def g(x, N):\n    return 0\n",
    "oracle_generator_code": "def make_oracle(secret, N):\n    def f(x):\n        dot = 0\n        for i in range(N):\n            if (secret & (1 << i)) and (x & (1 << i)):\n                dot ^= 1\n        return dot\n    return f\n"
  },
  {
    "problem_name": "Bernstein-Vazirani",
    "description": "Find a hidden bitstring s in a function f(x) = s * x (mod 2).",
    "completed_at": "2026-06-12T19:55:41.610094Z",
    "success_rate": 1.0,
    "quantum_query_complexity": "O(1)",
    "quantum_gate_complexity": "O(N)",
    "speedup_type": "Linear",
    "synthesis_code": "from qiskit import QuantumCircuit\nqc = QuantumCircuit(N + 1, N)\nqc.x(N)\nqc.h(range(N + 1))\nqc.compose(oracle, inplace=True)\nqc.h(range(N))\nqc.measure(range(N), range(N))\n",
    "analysis_text": "The quantum algorithm runs in 1 query, whereas classical deterministic search requires N queries. Thus, we achieve a linear speedup. The gate complexity is linear O(N) due to the single-qubit Hadamard gates applied before and after the oracle.",
    "base_function_code": "def g(x, N):\n    return 0\n",
    "oracle_generator_code": "def make_oracle(secret, N):\n    def f(x):\n        dot = 0\n        for i in range(N):\n            if (secret & (1 << i)) and (x & (1 << i)):\n                dot ^= 1\n        return dot\n    return f\n"
  },
  {
    "problem_name": "Bernstein-Vazirani",
    "description": "Find a hidden bitstring s in a function f(x) = s * x (mod 2).",
    "completed_at": "2026-06-12T19:40:28.050035Z",
    "success_rate": 1.0,
    "quantum_query_complexity": "O(1)",
    "quantum_gate_complexity": "O(N)",
    "speedup_type": "Linear",
    "synthesis_code": "from qiskit import QuantumCircuit\nqc = QuantumCircuit(N + 1, N)\nqc.x(N)\nqc.h(range(N + 1))\nqc.compose(oracle, inplace=True)\nqc.h(range(N))\nqc.measure(range(N), range(N))\n",
    "analysis_text": "The quantum algorithm runs in 1 query, whereas classical deterministic search requires N queries. Thus, we achieve a linear speedup. The gate complexity is linear O(N) due to the single-qubit Hadamard gates applied before and after the oracle.",
    "base_function_code": "def g(x, N):\n    return 0\n",
    "oracle_generator_code": "def make_oracle(secret, N):\n    def f(x):\n        dot = 0\n        for i in range(N):\n            if (secret & (1 << i)) and (x & (1 << i)):\n                dot ^= 1\n        return dot\n    return f\n"
  },
  {
    "problem_name": "Bernstein-Vazirani Problem",
    "description": "Given a black-box function f:{0,1}^N -> {0,1} which computes f(x) = (s . x) mod 2 for some secret N-bit string s. The goal is to find s. Quantum computers can find s with a single query, while classical computers require N queries in the worst case.",
    "completed_at": "2026-06-12T19:25:15.192925Z",
    "success_rate": 1.0,
    "quantum_query_complexity": "N/A",
    "quantum_gate_complexity": "N/A",
    "speedup_type": "N/A",
    "synthesis_code": "from qiskit import QuantumCircuit, QuantumRegister, ClassicalRegister\n\n# Define the number of input qubits (N) based on the problem and search results.\nN = 3\n\n# For demonstration, let's assume a secret string, e.g., '101' (decimal 5).\n# In a real run, this 'secret' would be unknown and is what we are trying to find.\nsecret_decimal = 5\n\n# Create quantum and classical registers\nqr_x = QuantumRegister(N, 'x')       # N qubits for the input x\nqr_anc = QuantumRegister(1, 'ancilla') # 1 ancilla qubit for the output f(x)\ncr_result = ClassicalRegister(N, 'c') # N classical bits to store the result\n\nqc = QuantumCircuit(qr_x, qr_anc, cr_result)\n\n# --- Pre-gates ---\n# Initialize the ancilla qubit to the |-> state (H|1>).\n# This sets up the phase kickback mechanism.\nqc.x(qr_anc[0])\nqc.h(qr_anc[0])\n\n# Apply Hadamard gates to all input qubits (qr_x) to create an equal superposition.\nfor i in range(N):\n    qc.h(qr_x[i])\n\nqc.barrier() # Separator for clarity\n\n# --- Oracle (black-box function f(x) = (s . x) mod 2) ---\n# The oracle applies a CNOT gate from qr_x[i] to qr_anc[0] for each bit i\n# where the i-th bit of the secret string 's' is 1.\n# This implements the bitwise dot product modulo 2.\n# The phase kickback ensures that the phase (-1)^f(x) is imprinted on the |x> states.\nfor i in range(N):\n    # Check the i-th bit of the secret (assuming qr_x[i] corresponds to x_i)\n    if (secret_decimal >> i) & 1:\n        qc.cx(qr_x[i], qr_anc[0])\n\nqc.barrier() # Separator for clarity\n\n# --- Mid-gates (None for Bernstein-Vazirani) ---\n# Bernstein-Vazirani is a single-query algorithm, so no mid-gates are needed.\n\n# --- Post-gates ---\n# Apply Hadamard gates to all input qubits again.\n# This transforms the phase information into amplitude information, \n# effectively rotating the state to |s>.\nfor i in range(N):\n    qc.h(qr_x[i])\n\nqc.barrier() # Separator for clarity\n\n# --- Measurement ---\n# Measure the input qubits (qr_x) and store the results in classical bits (cr_result).\n# The measurement will yield the secret string 's' with 100% probability.\nfor i in range(N):\n    qc.measure(qr_x[i], cr_result[i])\n\n# The circuit object 'qc' now holds the complete Bernstein-Vazirani circuit.",
    "analysis_text": "",
    "base_function_code": "def g(x, N):\n    \"\"\"\n    For Bernstein-Vazirani, the 'base' function can simply return the input x.\n    It represents the N-bit integer itself.\n    \"\"\"\n    return x",
    "oracle_generator_code": "def make_oracle(secret, N):\n    \"\"\"\n    Generates an oracle for the Bernstein-Vazirani problem.\n    The oracle function f(x) computes the bitwise dot product of 'secret' and 'x' modulo 2.\n    \"\"\"\n    def f(x):\n        # Calculate the bitwise dot product (sum of products of corresponding bits modulo 2)\n        result = 0\n        for i in range(N):\n            s_i = (secret >> i) & 1 # Get the i-th bit of secret\n            x_i = (x >> i) & 1     # Get the i-th bit of x\n            result = (result + s_i * x_i) % 2 # Add product and take modulo 2\n        return result\n    return f"
  },
  {
    "problem_name": "Bernstein-Vazirani Problem",
    "description": "Given a function f(x) = a . x (mod 2) for a secret N-bit string 'a', find 'a'. Classically requires N queries, quantumly 1 query. The dot product 'a . x' is the bitwise dot product.",
    "completed_at": "2026-06-12T19:07:18.166950Z",
    "success_rate": 1.0,
    "quantum_query_complexity": "O(1)",
    "quantum_gate_complexity": "O(N)",
    "speedup_type": "Linear speedup in query complexity",
    "synthesis_code": "from qiskit import QuantumCircuit, QuantumRegister, ClassicalRegister\n\n# --- Configuration based on search results ---\n# Determine the number of input qubits (N) from the length of pre-gates\n# Pre-Gates: [('H', 'H', 'H')] -> N = 3\nN = len(['H', 'H', 'H']) # N input qubits\n\n# Create quantum and classical registers\n# N input qubits (for x), 1 ancilla qubit (for f(x))\nqr = QuantumRegister(N + 1, 'q')\ncr = ClassicalRegister(N, 'c')\nqc = QuantumCircuit(qr, cr)\n\n# --- Example secret 'a' for demonstration purposes ---\n# In the actual Bernstein-Vazirani problem, 'a' is unknown.\n# The oracle effectively encodes this secret.\n# Let's assume a secret 'a' = 5 (binary '101' for N=3)\n# This means a_0=1, a_1=0, a_2=1 (little-endian, a_i corresponds to qr[i])\nexample_secret_a_bits = [1, 0, 1] # Corresponds to secret '101'\n\n# 1. Pre-gates\n# Apply Hadamard gates to all N input qubits\nfor i in range(N):\n    qc.h(qr[i])\n# Prepare the ancilla qubit (qr[N]) in the |-> state\nqc.x(qr[N])\nqc.h(qr[N])\nqc.barrier()\n\n# 2. Oracle (implements f(x) = a.x mod 2 using phase kickback)\n# The oracle is constructed based on the bits of the secret 'a'.\n# For each bit a_i in the secret: if a_i is 1, apply a CX gate\n# with qr[i] as control and the ancilla qubit qr[N] as target.\n# If a_i is 0, no gate is applied for that qubit.\nfor i in range(N):\n    if example_secret_a_bits[i] == 1:\n        qc.cx(qr[i], qr[N]) # CX from input qubit i to ancilla\nqc.barrier()\n\n# 3. Mid-gates (none for this problem according to search results)\n# mid_gates = []\n\n# 4. Post-gates\n# Apply Hadamard gates to all N input qubits\nfor i in range(N):\n    qc.h(qr[i])\nqc.barrier()\n\n# 5. Measurement\n# Measure the N input qubits to read out the secret 'a'\nfor i in range(N):\n    qc.measure(qr[i], cr[i])",
    "analysis_text": "The Bernstein-Vazirani problem requires finding a secret N-bit string 'a' from a black-box function f(x) = a . x (mod 2). Classically, determining 'a' requires N queries to the function, as each bit a_i must be individually probed (e.g., by querying f(e_i) where e_i is a bit string with 1 at position i and 0 elsewhere). This leads to a classical query complexity of O(N). Computationally, this also translates to O(N) classical operations.\n\nQuantum mechanically, the Bernstein-Vazirani algorithm provides a dramatic speedup in query complexity. By preparing an N-qubit input register in a superposition state, applying a Hadamard transform, querying the oracle exactly once (U_f), and then applying another Hadamard transform before measurement, the secret string 'a' can be determined with certainty. This results in a quantum query complexity of O(1).\n\nIn terms of gate complexity, the quantum algorithm requires O(N) Hadamard gates for preparing and collapsing the superposition of the input register, plus O(1) gates for the ancilla qubit. The oracle itself, if implemented non-generically (e.g., as a series of CNOT gates controlled by the 'a' string), also contributes O(N) gates. Thus, the total quantum gate complexity is O(N).\n\nComparing complexities: The quantum algorithm achieves a query complexity of O(1) while the classical algorithm requires O(N) queries. This constitutes a linear speedup in query complexity (O(N) / O(1) = O(N)). In terms of total computational operations (gates vs. elementary classical operations), both the quantum and classical algorithms exhibit O(N) scaling, assuming the oracle implementation is counted. The provided scaling data for N=2 and N=3 shows perfect success (1.0), which is expected for ideal simulations of the Bernstein-Vazirani algorithm. The reported 'non-oracle' circuit depth (2) and gate counts ({'x': 1, 'h': 1}) are consistently minimal and likely refer to a specific component, such as the ancilla qubit preparation, rather than the total non-oracle gates for N input qubits (which would be 2N Hadamards for the input register).",
    "base_function_code": "def g(x, N):\n    # This function simply returns the input x.\n    # In the context of oracle-based problems, x is typically the input to the oracle.\n    return x",
    "oracle_generator_code": "def make_oracle(secret, N):\n    # Convert secret integer to a list of bits (little-endian for consistency)\n    secret_bits = [(secret >> i) & 1 for i in range(N)]\n    \n    def f(x):\n        # Convert input x integer to a list of bits (little-endian)\n        x_bits = [(x >> i) & 1 for i in range(N)]\n        \n        dot_product_sum = 0\n        for i in range(N):\n            dot_product_sum += x_bits[i] * secret_bits[i]\n        \n        return dot_product_sum % 2\n    return f"
  },
  {
    "problem_name": "Bernstein-Vazirani Problem",
    "description": "The goal is to find a secret N-bit string 's' such that an oracle function f(x) computes the bitwise dot product of x and s, modulo 2 (f(x) = (x . s) mod 2). A quantum computer can find 's' in a single query to the oracle, while a classical computer generally requires N queries.",
    "completed_at": "2026-06-12T18:59:40.710742Z",
    "success_rate": 1.0,
    "quantum_query_complexity": "O(1)",
    "quantum_gate_complexity": "O(N)",
    "speedup_type": "Linear speedup in query complexity",
    "synthesis_code": "from qiskit import QuantumCircuit, QuantumRegister, ClassicalRegister\n\ndef bernstein_vazirani_circuit(secret_int):\n    # N is determined from the problem's context (e.g., pre-gates length).\n    # For this problem, N=3 as indicated by ('H','H','H') pre-gates.\n    N = 3 \n    \n    # Define quantum registers for the N data qubits and 1 ancilla qubit\n    data_qr = QuantumRegister(N, 'x')\n    ancilla_qr = QuantumRegister(1, 'ancilla')\n    # Define a classical register to store the measurement results\n    c_reg = ClassicalRegister(N, 'c')\n    \n    # Create the quantum circuit\n    qc = QuantumCircuit(data_qr, ancilla_qr, c_reg)\n    \n    # Pre-gates: Apply Hadamard gates to all data qubits to create a superposition,\n    # and prepare the ancilla qubit in the |-\\u003e state (|0\\u003e - |1\\u003e)/sqrt(2)\n    # for phase kickback.\n    qc.h(data_qr)\n    qc.x(ancilla_qr[0])\n    qc.h(ancilla_qr[0])\n    qc.barrier()\n    \n    # Oracle construction: Implements f(x) = (x . s) mod 2\n    # This is done by applying a CNOT gate for each bit i where s_i is 1.\n    # The control is data_qr[i] and the target is ancilla_qr[0].\n    for i in range(N):\n        # Check if the i-th bit of the secret_int is 1\n        if (secret_int >> i) & 1:\n            qc.cx(data_qr[i], ancilla_qr[0])\n    qc.barrier()\n            \n    # Mid-gates: No mid-gates were found in the search results.\n    \n    # Post-gates: Apply Hadamard gates to all data qubits.\n    qc.h(data_qr)\n    qc.barrier()\n    \n    # Measure the data qubits to obtain the secret string\n    qc.measure(data_qr, c_reg)\n    \n    return qc\n\n# --- Example Usage ---\n# To find a 3-bit secret (e.g., s = 101 in binary, which is 5 in decimal):\n# secret_to_find = 5 \n# bv_circuit = bernstein_vazirani_circuit(secret_to_find)\n# print(bv_circuit.draw(output='text', idle_wires=False))",
    "analysis_text": "The Bernstein-Vazirani problem demonstrates a significant advantage for quantum computation in terms of query complexity. A classical algorithm, in the worst case, must query the oracle function f(x) for N distinct input strings (e.g., basis vectors e_i) to fully determine the N-bit secret string 's'. This leads to a classical query complexity of O(N) and an overall computational complexity of O(N). In contrast, the quantum algorithm, leveraging superposition and interference, can determine the secret string 's' with a single query to the quantum oracle. This establishes a quantum query complexity of O(1).\n\nRegarding gate complexity, the quantum algorithm typically involves 2N Hadamard gates (N before and N after the oracle), an X gate and a Hadamard gate on an ancilla qubit, and the oracle itself. The quantum oracle, which implements the function f(x) = (x . s) mod 2, can be constructed using O(N) CNOT gates in the worst case, depending on the secret string 's'. Therefore, the total quantum gate complexity scales linearly with N, i.e., O(N). The provided scaling data for 'non-oracle' gates (Gate Counts: {'x': 1, 'h': 1}, Circuit Depth: 2) appears to capture a fixed overhead component (e.g., ancilla preparation) rather than the N-dependent scaling of the full circuit, which includes the 2N Hadamards and the oracle.\n\nComparing the complexities: the quantum algorithm achieves an O(1) query complexity versus the classical O(N). This represents a linear speedup in the number of queries required. In terms of overall computational steps or gate counts, both the quantum and classical algorithms scale as O(N), implying a constant factor speedup for quantum computation in this metric. The problem's core advantage is best expressed through its query complexity.\n\nThe collected data shows a perfect Success Rate of 1.0 for N=2 and N=3 qubits, which is expected as the Bernstein-Vazirani algorithm is deterministic and provides the correct answer with certainty in an ideal quantum computer.",
    "base_function_code": "def g(x, N):\n    # This 'base function' is not directly the oracle itself.\n    # For Bernstein-Vazirani, the oracle (defined in make_oracle) uses\n    # the input x to compute a value based on a secret 's'.\n    # This function simply returns x, which is then processed by the oracle.\n    return x",
    "oracle_generator_code": "def make_oracle(secret, N):\n    # The secret 's' is an N-bit integer.\n    # The oracle function f(x) computes (x . s) mod 2.\n    # This is done by summing the products of corresponding bits of x and s,\n    # and then taking the sum modulo 2.\n    def f(x):\n        dot_product_sum = 0\n        for i in range(N):\n            # Extract the i-th bit of x and secret\n            x_i = (x >> i) & 1\n            s_i = (secret >> i) & 1\n            dot_product_sum += x_i * s_i\n        return dot_product_sum % 2\n    return f"
  },
  {
    "problem_name": "Bernstein-Vazirani",
    "description": "The Bernstein-Vazirani problem asks to find a secret N-bit string 'a' given an oracle that computes f(x) = (a AND x) % 2, i.e., the dot product of x and a modulo 2. A quantum computer can find 'a' with a single query to the oracle.",
    "completed_at": "2026-06-12T18:54:46.503937Z",
    "success_rate": 1.0,
    "quantum_query_complexity": "O(1)",
    "quantum_gate_complexity": "O(N)",
    "speedup_type": "Polynomial",
    "synthesis_code": "from qiskit import QuantumCircuit\n\ndef build_bernstein_vazirani_circuit(secret_int, N):\n    \"\"\"\n    Constructs a Qiskit circuit for the Bernstein-Vazirani algorithm.\n\n    Args:\n        secret_int (int): The integer representing the N-bit secret string 'a'.\n                          (e.g., 5 for binary '101' if N=3).\n        N (int): The number of bits in the secret string (number of data qubits).\n\n    Returns:\n        QuantumCircuit: The Qiskit circuit for Bernstein-Vazirani.\n    \"\"\"\n    # N data qubits (for input x) + 1 ancilla qubit (for f(x))\n    qc = QuantumCircuit(N + 1, N)\n\n    # Pre-gates: Apply H to all data qubits\n    # Search results indicated [('H', 'H', 'H')] for N=3 data qubits\n    for i in range(N):\n        qc.h(i)\n\n    # Prepare the ancilla qubit in the |-> state (|0>-|1>)/sqrt(2)\n    qc.x(N) # Apply X gate to change |0> to |1>\n    qc.h(N) # Apply H gate to change |1> to |->\n\n    qc.barrier(label=\"Preparation\")\n\n    # Oracle: Implements f(x) = (x . secret) mod 2\n    # For each bit in the secret_int, if it's 1, apply a CX gate\n    # from the corresponding data qubit to the ancilla qubit.\n    for i in range(N):\n        if (secret_int >> i) & 1: # Check the i-th bit of the secret\n            qc.cx(i, N)\n\n    qc.barrier(label=\"Oracle\")\n\n    # Post-gates: Apply H to all data qubits\n    # Search results indicated [('H', 'H', 'H')] for N=3 data qubits\n    for i in range(N):\n        qc.h(i)\n\n    # Measure the data qubits to read out the secret string 'a'\n    for i in range(N):\n        qc.measure(i, i)\n\n    return qc\n\n# Example usage with N=3 and a secret value of 5 (binary '101')\n# This value for N is inferred from the search results showing 3 H gates.\nnum_qubits = 3\nsecret_value_int = 5 # Represents the binary string '101'\nbv_circuit = build_bernstein_vazirani_circuit(secret_value_int, num_qubits)\n\n# You can print the circuit or run it on a simulator:\n# print(bv_circuit.draw(output='text'))\n\n# To verify, you would run this circuit on a simulator\n# and expect to measure '101' with 100% probability.\n# from qiskit_aer import AerSimulator\n# from qiskit import transpile\n# simulator = AerSimulator()\n# compiled_circuit = transpile(bv_circuit, simulator)\n# job = simulator.run(compiled_circuit, shots=1)\n# result = job.result()\n# counts = result.get_counts(bv_circuit)\n# print(\"Measurement result:\", counts) # Expected: {'101': 1}",
    "analysis_text": "The Bernstein-Vazirani problem aims to discover a secret N-bit string 'a' using an oracle that computes the dot product of an input 'x' with 'a' modulo 2. Classically, this problem requires a minimum of N oracle queries to determine each bit of 'a' individually. For example, to find the i-th bit, one can query with 'x' being 1 at the i-th position and 0 elsewhere. This leads to a classical query complexity of O(N). If each query (dot product computation) itself takes O(N) operations, the total classical computational complexity would be O(N^2).\n\nIn contrast, the quantum Bernstein-Vazirani algorithm leverages superposition and interference to determine the secret string 'a' with just a single query to the oracle. This remarkable efficiency yields a quantum query complexity of O(1). The quantum circuit typically consists of N Hadamard gates on the input qubits before the oracle, the oracle itself (which involves N controlled-NOT gates for a standard implementation), and N Hadamard gates after the oracle, along with initial preparation of an ancilla qubit. Therefore, the overall quantum gate complexity scales linearly with N, i.e., O(N).\n\nThe provided scaling data shows a perfect success rate (1.0) for N=2 and N=3, which is expected for this deterministic quantum algorithm under ideal simulation conditions. The 'non-oracle' circuit depth of 2 and gate counts {'x': 1, 'h': 1} for these N values likely represent the fixed overhead associated with preparing the ancilla qubit to the |-> state, which does not scale with N, rather than the core N-dependent operations.\n\nComparing the complexities, the quantum algorithm offers a significant polynomial speedup in terms of query complexity, reducing an O(N) classical requirement to an O(1) quantum requirement. This means the time to find 'a' does not grow with the size of 'a' in the quantum case, which is a powerful demonstration of quantum computational advantage over classical algorithms for this specific problem.",
    "base_function_code": "def g(x, N):\n    # This function computes the parity (sum of bits mod 2) of x.\n    # It serves as a representative example of a linear function.\n    count = 0\n    for i in range(N):\n        if (x >> i) & 1:\n            count += 1\n    return count % 2",
    "oracle_generator_code": "def make_oracle(secret, N):\n    # The oracle for Bernstein-Vazirani computes f(x) = (x . secret) mod 2.\n    # 'secret' is an N-bit integer representing the string 'a'.\n    # 'x' is an N-bit integer input.\n    def f(x):\n        dot_product = 0\n        for i in range(N):\n            x_bit = (x >> i) & 1\n            secret_bit = (secret >> i) & 1\n            dot_product += x_bit * secret_bit\n        return dot_product % 2\n    return f"
  }
]