{
  "status": "searching",
  "last_updated": "2026-06-18T07:06:36.684985Z",
  "current_run": {
    "problem_name": "Hidden Cubic Bit-Product Shift",
    "description": "This problem hides a secret cubic function of three bits, f(x_i, x_j, x_k) = s * x_i * x_j * x_k mod 2, where 's' is a secret bit. The oracle computes a shifted version of this function: O(x) = f(x) XOR (a . x), where 'a' is a known vector and '.' is the dot product. The goal is to find 's'. This is a non-linear problem that is not a direct reduction to known algorithms. The linear part (a.x) is designed to be a distractor and potentially require some linear algebra to isolate the cubic term if not handled carefully.",
    "stage": "analyzing",
    "started_at": "2026-06-18T07:06:36.685039Z"
  }
}